pydantic_serializer/__init__.py
pydantic_serializer/deserializer.py
pydantic_serializer-0.2.1.dist-info/METADATA
pydantic_serializer-0.2.1.dist-info/WHEEL
pydantic_serializer-0.2.1.dist-info/RECORD
