Metadata-Version: 2.1
Name: pydantic-serializer
Version: 0.2.1
Summary: A decorator to serialize a string into a Pydantic model with error handling
Author: softmaxer
Author-email: sriram.vadlamani@proton.me
Requires-Python: >=3.12,<4.0
Classifier: Programming Language :: Python :: 3
Classifier: Programming Language :: Python :: 3.12
Requires-Dist: loguru (>=0.7.2,<0.8.0)
Requires-Dist: pydantic (>=2.8.2,<3.0.0)
